[
  {
    "fields": [
      {
        "validation": [
          {
            "rules": [
              {
                "flag": "presence",
                "constraint": "required"
              }
            ],
            "level": "error"
          }
        ],
        "name": "name",
        "type": "string"
      },
      {
        "validation": [
          {
            "rules": [
              {
                "flag": "presence",
                "constraint": "required"
              }
            ],
            "level": "error"
          }
        ],
        "of": [
          {
            "marks": {
              "annotations": [
                {
                  "i18nTitleKey": "inputs.portable-text.annotation.link",
                  "options": {
                    "modal": {
                      "type": "popover"
                    }
                  },
                  "fields": [
                    {
                      "validation": [
                        {
                          "rules": [
                            {
                              "flag": "uri",
                              "constraint": {
                                "options": {
                                  "scheme": [
                                    "/^http$/",
                                    "/^https$/",
                                    "/^tel$/",
                                    "/^mailto$/"
                                  ],
                                  "allowRelative": true,
                                  "relativeOnly": false,
                                  "allowCredentials": false
                                }
                              }
                            }
                          ],
                          "level": "error"
                        }
                      ],
                      "description": "A valid web, email, phone, or relative link.",
                      "name": "href",
                      "type": "url",
                      "title": "Link"
                    }
                  ],
                  "name": "link",
                  "type": "object"
                }
              ],
              "decorators": [
                {
                  "value": "strong",
                  "title": "Strong"
                },
                {
                  "value": "em",
                  "title": "Italic"
                },
                {
                  "value": "code",
                  "title": "Code"
                },
                {
                  "value": "underline",
                  "title": "Underline"
                },
                {
                  "value": "strike-through",
                  "title": "Strike"
                }
              ]
            },
            "lists": [
              {
                "value": "bullet",
                "title": "Bulleted list"
              },
              {
                "value": "number",
                "title": "Numbered list"
              }
            ],
            "styles": [
              {
                "value": "normal",
                "title": "Normal"
              },
              {
                "value": "h1",
                "title": "Heading 1"
              },
              {
                "value": "h2",
                "title": "Heading 2"
              },
              {
                "value": "h3",
                "title": "Heading 3"
              },
              {
                "value": "h4",
                "title": "Heading 4"
              },
              {
                "value": "h5",
                "title": "Heading 5"
              },
              {
                "value": "h6",
                "title": "Heading 6"
              },
              {
                "value": "blockquote",
                "title": "Quote"
              }
            ],
            "of": [],
            "type": "block"
          }
        ],
        "name": "description",
        "type": "array"
      },
      {
        "options": {
          "source": "name"
        },
        "validation": [
          {
            "rules": [
              {
                "flag": "custom"
              },
              {
                "flag": "presence",
                "constraint": "required"
              }
            ],
            "level": "error"
          }
        ],
        "name": "slug",
        "type": "slug"
      },
      {
        "validation": [
          {
            "rules": [
              {
                "flag": "presence",
                "constraint": "required"
              }
            ],
            "level": "error"
          }
        ],
        "name": "seo",
        "type": "seo",
        "title": "SEO"
      },
      {
        "name": "date",
        "type": "datetime"
      },
      {
        "name": "venue",
        "type": "string"
      },
      {
        "options": {
          "hotspot": true
        },
        "validation": [
          {
            "rules": [
              {
                "flag": "presence",
                "constraint": "required"
              }
            ],
            "level": "error"
          }
        ],
        "fields": [
          {
            "name": "alt",
            "type": "string",
            "title": "Alt Text"
          }
        ],
        "name": "image",
        "type": "image"
      },
      {
        "name": "price",
        "type": "number"
      },
      {
        "of": [
          {
            "type": "button"
          }
        ],
        "name": "buttons",
        "type": "array"
      },
      {
        "validation": [
          {
            "rules": [
              {
                "flag": "presence",
                "constraint": "required"
              }
            ],
            "level": "error"
          }
        ],
        "of": [
          {
            "marks": {
              "annotations": [
                {
                  "i18nTitleKey": "inputs.portable-text.annotation.link",
                  "options": {
                    "modal": {
                      "type": "popover"
                    }
                  },
                  "fields": [
                    {
                      "validation": [
                        {
                          "rules": [
                            {
                              "flag": "uri",
                              "constraint": {
                                "options": {
                                  "scheme": [
                                    "/^http$/",
                                    "/^https$/",
                                    "/^tel$/",
                                    "/^mailto$/"
                                  ],
                                  "allowRelative": true,
                                  "relativeOnly": false,
                                  "allowCredentials": false
                                }
                              }
                            }
                          ],
                          "level": "error"
                        }
                      ],
                      "description": "A valid web, email, phone, or relative link.",
                      "name": "href",
                      "type": "url",
                      "title": "Link"
                    }
                  ],
                  "name": "link",
                  "type": "object"
                }
              ],
              "decorators": [
                {
                  "value": "strong",
                  "title": "Strong"
                },
                {
                  "value": "em",
                  "title": "Italic"
                },
                {
                  "value": "code",
                  "title": "Code"
                },
                {
                  "value": "underline",
                  "title": "Underline"
                },
                {
                  "value": "strike-through",
                  "title": "Strike"
                }
              ]
            },
            "lists": [
              {
                "value": "bullet",
                "title": "Bulleted list"
              },
              {
                "value": "number",
                "title": "Numbered list"
              }
            ],
            "styles": [
              {
                "value": "normal",
                "title": "Normal"
              },
              {
                "value": "h1",
                "title": "Heading 1"
              },
              {
                "value": "h2",
                "title": "Heading 2"
              },
              {
                "value": "h3",
                "title": "Heading 3"
              },
              {
                "value": "h4",
                "title": "Heading 4"
              },
              {
                "value": "h5",
                "title": "Heading 5"
              },
              {
                "value": "h6",
                "title": "Heading 6"
              },
              {
                "value": "blockquote",
                "title": "Quote"
              }
            ],
            "of": [],
            "type": "block"
          }
        ],
        "name": "details",
        "type": "array"
      }
    ],
    "name": "event",
    "type": "document"
  },
  {
    "fields": [
      {
        "validation": [
          {
            "rules": [
              {
                "flag": "presence",
                "constraint": "required"
              }
            ],
            "level": "error"
          }
        ],
        "name": "title",
        "type": "string"
      },
      {
        "options": {
          "list": [
            {
              "title": "High Impact",
              "value": "high-impact"
            },
            {
              "title": "Low Impact",
              "value": "low-impact"
            }
          ]
        },
        "validation": [
          {
            "rules": [
              {
                "flag": "valid",
                "constraint": ["high-impact", "low-impact"]
              },
              {
                "flag": "presence",
                "constraint": "required"
              }
            ],
            "level": "error"
          }
        ],
        "name": "intent",
        "type": "string"
      },
      {
        "validation": [
          {
            "rules": [
              {
                "flag": "presence",
                "constraint": "required"
              }
            ],
            "level": "error"
          }
        ],
        "of": [
          {
            "marks": {
              "annotations": [
                {
                  "i18nTitleKey": "inputs.portable-text.annotation.link",
                  "options": {
                    "modal": {
                      "type": "popover"
                    }
                  },
                  "fields": [
                    {
                      "validation": [
                        {
                          "rules": [
                            {
                              "flag": "uri",
                              "constraint": {
                                "options": {
                                  "scheme": [
                                    "/^http$/",
                                    "/^https$/",
                                    "/^tel$/",
                                    "/^mailto$/"
                                  ],
                                  "allowRelative": true,
                                  "relativeOnly": false,
                                  "allowCredentials": false
                                }
                              }
                            }
                          ],
                          "level": "error"
                        }
                      ],
                      "description": "A valid web, email, phone, or relative link.",
                      "name": "href",
                      "type": "url",
                      "title": "Link"
                    }
                  ],
                  "name": "link",
                  "type": "object"
                }
              ],
              "decorators": [
                {
                  "value": "strong",
                  "title": "Strong"
                },
                {
                  "value": "em",
                  "title": "Italic"
                },
                {
                  "value": "code",
                  "title": "Code"
                },
                {
                  "value": "underline",
                  "title": "Underline"
                },
                {
                  "value": "strike-through",
                  "title": "Strike"
                }
              ]
            },
            "lists": [
              {
                "value": "bullet",
                "title": "Bulleted list"
              },
              {
                "value": "number",
                "title": "Numbered list"
              }
            ],
            "styles": [
              {
                "value": "normal",
                "title": "Normal"
              },
              {
                "value": "h1",
                "title": "Heading 1"
              },
              {
                "value": "h2",
                "title": "Heading 2"
              },
              {
                "value": "h3",
                "title": "Heading 3"
              },
              {
                "value": "h4",
                "title": "Heading 4"
              },
              {
                "value": "h5",
                "title": "Heading 5"
              },
              {
                "value": "h6",
                "title": "Heading 6"
              },
              {
                "value": "blockquote",
                "title": "Quote"
              }
            ],
            "of": [],
            "type": "block"
          }
        ],
        "name": "text",
        "type": "array"
      },
      {
        "of": [
          {
            "type": "button"
          }
        ],
        "name": "buttons",
        "type": "array"
      },
      {
        "validation": [
          {
            "rules": [
              {
                "flag": "presence",
                "constraint": "required"
              }
            ],
            "level": "error"
          }
        ],
        "fields": [
          {
            "name": "alt",
            "type": "string",
            "title": "Alt Text"
          }
        ],
        "name": "backgroundImage",
        "type": "image"
      }
    ],
    "name": "hero",
    "type": "object"
  },
  {
    "of": [
      {
        "type": "hero"
      },
      {
        "type": "splitImage"
      },
      {
        "type": "prose"
      },
      {
        "type": "events"
      }
    ],
    "name": "pageBuilder",
    "type": "array"
  },
  {
    "fields": [
      {
        "validation": [
          {
            "rules": [
              {
                "flag": "presence",
                "constraint": "required"
              }
            ],
            "level": "error"
          }
        ],
        "name": "title",
        "type": "string"
      },
      {
        "options": {
          "source": "title"
        },
        "validation": [
          {
            "rules": [
              {
                "flag": "custom"
              },
              {
                "flag": "presence",
                "constraint": "required"
              }
            ],
            "level": "error"
          }
        ],
        "name": "slug",
        "type": "slug"
      },
      {
        "validation": [
          {
            "rules": [
              {
                "flag": "presence",
                "constraint": "required"
              }
            ],
            "level": "error"
          }
        ],
        "name": "seo",
        "type": "seo",
        "title": "SEO"
      },
      {
        "validation": [
          {
            "rules": [
              {
                "flag": "presence",
                "constraint": "required"
              }
            ],
            "level": "error"
          }
        ],
        "name": "content",
        "type": "pageBuilder"
      }
    ],
    "name": "page",
    "type": "document"
  },
  {
    "fields": [
      {
        "options": {
          "list": [
            {
              "value": "imageLeft",
              "title": "Image Left"
            },
            {
              "value": "imageRight",
              "title": "Image Right"
            }
          ]
        },
        "validation": [
          {
            "rules": [
              {
                "flag": "valid",
                "constraint": ["imageLeft", "imageRight"]
              },
              {
                "flag": "presence",
                "constraint": "required"
              }
            ],
            "level": "error"
          }
        ],
        "name": "orientation",
        "type": "string"
      },
      {
        "validation": [
          {
            "rules": [
              {
                "flag": "presence",
                "constraint": "required"
              }
            ],
            "level": "error"
          }
        ],
        "name": "title",
        "type": "string"
      },
      {
        "options": {
          "hotspot": true
        },
        "validation": [
          {
            "rules": [
              {
                "flag": "presence",
                "constraint": "required"
              }
            ],
            "level": "error"
          }
        ],
        "fields": [
          {
            "name": "alt",
            "type": "string",
            "title": "Alt Text"
          }
        ],
        "name": "image",
        "type": "image"
      },
      {
        "validation": [
          {
            "rules": [
              {
                "flag": "presence",
                "constraint": "required"
              }
            ],
            "level": "error"
          }
        ],
        "of": [
          {
            "marks": {
              "annotations": [
                {
                  "i18nTitleKey": "inputs.portable-text.annotation.link",
                  "options": {
                    "modal": {
                      "type": "popover"
                    }
                  },
                  "fields": [
                    {
                      "validation": [
                        {
                          "rules": [
                            {
                              "flag": "uri",
                              "constraint": {
                                "options": {
                                  "scheme": [
                                    "/^http$/",
                                    "/^https$/",
                                    "/^tel$/",
                                    "/^mailto$/"
                                  ],
                                  "allowRelative": true,
                                  "relativeOnly": false,
                                  "allowCredentials": false
                                }
                              }
                            }
                          ],
                          "level": "error"
                        }
                      ],
                      "description": "A valid web, email, phone, or relative link.",
                      "name": "href",
                      "type": "url",
                      "title": "Link"
                    }
                  ],
                  "name": "link",
                  "type": "object"
                }
              ],
              "decorators": [
                {
                  "value": "strong",
                  "title": "Strong"
                },
                {
                  "value": "em",
                  "title": "Italic"
                },
                {
                  "value": "code",
                  "title": "Code"
                },
                {
                  "value": "underline",
                  "title": "Underline"
                },
                {
                  "value": "strike-through",
                  "title": "Strike"
                }
              ]
            },
            "lists": [
              {
                "value": "bullet",
                "title": "Bulleted list"
              },
              {
                "value": "number",
                "title": "Numbered list"
              }
            ],
            "styles": [
              {
                "value": "normal",
                "title": "Normal"
              },
              {
                "value": "h1",
                "title": "Heading 1"
              },
              {
                "value": "h2",
                "title": "Heading 2"
              },
              {
                "value": "h3",
                "title": "Heading 3"
              },
              {
                "value": "h4",
                "title": "Heading 4"
              },
              {
                "value": "h5",
                "title": "Heading 5"
              },
              {
                "value": "h6",
                "title": "Heading 6"
              },
              {
                "value": "blockquote",
                "title": "Quote"
              }
            ],
            "of": [],
            "type": "block"
          }
        ],
        "name": "text",
        "type": "array"
      }
    ],
    "name": "splitImage",
    "type": "object"
  },
  {
    "fields": [
      {
        "validation": [
          {
            "rules": [
              {
                "flag": "presence",
                "constraint": "required"
              }
            ],
            "level": "error"
          }
        ],
        "name": "title",
        "type": "string"
      },
      {
        "options": {
          "hotspot": true
        },
        "validation": [
          {
            "rules": [
              {
                "flag": "presence",
                "constraint": "required"
              }
            ],
            "level": "error"
          }
        ],
        "fields": [
          {
            "name": "alt",
            "type": "string",
            "title": "Alt Text"
          }
        ],
        "name": "logo",
        "type": "image"
      },
      {
        "validation": [
          {
            "rules": [
              {
                "flag": "presence",
                "constraint": "required"
              }
            ],
            "level": "error"
          }
        ],
        "of": [
          {
            "type": "link"
          }
        ],
        "name": "links",
        "type": "array"
      },
      {
        "validation": [
          {
            "rules": [
              {
                "flag": "presence",
                "constraint": "required"
              }
            ],
            "level": "error"
          }
        ],
        "of": [
          {
            "type": "social"
          }
        ],
        "name": "socials",
        "type": "array"
      }
    ],
    "name": "header",
    "type": "document"
  },
  {
    "fields": [
      {
        "validation": [
          {
            "rules": [
              {
                "flag": "presence",
                "constraint": "required"
              }
            ],
            "level": "error"
          }
        ],
        "name": "title",
        "type": "string"
      },
      {
        "validation": [
          {
            "rules": [
              {
                "flag": "presence",
                "constraint": "required"
              }
            ],
            "level": "error"
          }
        ],
        "name": "copyright",
        "type": "string"
      },
      {
        "validation": [
          {
            "rules": [
              {
                "flag": "presence",
                "constraint": "required"
              }
            ],
            "level": "error"
          }
        ],
        "of": [
          {
            "type": "link"
          }
        ],
        "name": "links",
        "type": "array"
      },
      {
        "validation": [
          {
            "rules": [
              {
                "flag": "presence",
                "constraint": "required"
              }
            ],
            "level": "error"
          }
        ],
        "of": [
          {
            "type": "social"
          }
        ],
        "name": "socials",
        "type": "array"
      }
    ],
    "name": "footer",
    "type": "document"
  },
  {
    "fields": [
      {
        "validation": [
          {
            "rules": [
              {
                "flag": "presence",
                "constraint": "required"
              }
            ],
            "level": "error"
          }
        ],
        "name": "title",
        "type": "string"
      },
      {
        "validation": [
          {
            "rules": [
              {
                "flag": "uri",
                "constraint": {
                  "options": {
                    "scheme": ["/^http$/", "/^https$/"],
                    "allowRelative": false,
                    "relativeOnly": false,
                    "allowCredentials": false
                  }
                }
              },
              {
                "flag": "presence",
                "constraint": "required"
              }
            ],
            "level": "error"
          }
        ],
        "name": "url",
        "type": "url",
        "title": "URL"
      },
      {
        "options": {
          "hotspot": true
        },
        "validation": [
          {
            "rules": [
              {
                "flag": "presence",
                "constraint": "required"
              }
            ],
            "level": "error"
          }
        ],
        "fields": [
          {
            "validation": [
              {
                "rules": [
                  {
                    "flag": "presence",
                    "constraint": "required"
                  }
                ],
                "level": "error"
              }
            ],
            "name": "alt",
            "type": "string",
            "title": "Alt Text"
          }
        ],
        "name": "icon",
        "type": "image"
      }
    ],
    "name": "social",
    "type": "document"
  },
  {
    "fields": [
      {
        "validation": [
          {
            "rules": [
              {
                "flag": "presence",
                "constraint": "required"
              }
            ],
            "level": "error"
          }
        ],
        "name": "link",
        "type": "link"
      },
      {
        "options": {
          "list": [
            {
              "title": "Default",
              "value": "default"
            },
            {
              "title": "Secondary",
              "value": "secondary"
            },
            {
              "title": "Destructive",
              "value": "destructive"
            },
            {
              "title": "Outline",
              "value": "outline"
            },
            {
              "title": "Ghost",
              "value": "ghost"
            }
          ]
        },
        "validation": [
          {
            "rules": [
              {
                "flag": "valid",
                "constraint": [
                  "default",
                  "secondary",
                  "destructive",
                  "outline",
                  "ghost"
                ]
              },
              {
                "flag": "presence",
                "constraint": "required"
              }
            ],
            "level": "error"
          }
        ],
        "name": "variant",
        "type": "string"
      },
      {
        "options": {
          "list": [
            {
              "title": "Default",
              "value": "default"
            },
            {
              "title": "Small",
              "value": "sm"
            },
            {
              "title": "Large",
              "value": "lg"
            }
          ]
        },
        "validation": [
          {
            "rules": [
              {
                "flag": "valid",
                "constraint": ["default", "sm", "lg"]
              },
              {
                "flag": "presence",
                "constraint": "required"
              }
            ],
            "level": "error"
          }
        ],
        "name": "size",
        "type": "string"
      }
    ],
    "name": "button",
    "type": "object"
  },
  {
    "fields": [
      {
        "validation": [
          {
            "rules": [
              {
                "flag": "presence",
                "constraint": "required"
              }
            ],
            "level": "error"
          }
        ],
        "name": "text",
        "type": "string"
      },
      {
        "validation": [
          {
            "rules": [
              {
                "flag": "presence",
                "constraint": "required"
              },
              {
                "flag": "uri",
                "constraint": {
                  "options": {
                    "scheme": [
                      "/^http$/",
                      "/^https$/",
                      "/^mailto$/",
                      "/^tel$/"
                    ],
                    "allowRelative": true,
                    "relativeOnly": false,
                    "allowCredentials": false
                  }
                }
              }
            ],
            "level": "error"
          }
        ],
        "name": "url",
        "type": "url",
        "title": "URL"
      }
    ],
    "name": "link",
    "type": "object"
  },
  {
    "fields": [
      {
        "validation": [
          {
            "rules": [
              {
                "flag": "presence",
                "constraint": "required"
              }
            ],
            "level": "error"
          }
        ],
        "of": [
          {
            "marks": {
              "annotations": [
                {
                  "i18nTitleKey": "inputs.portable-text.annotation.link",
                  "options": {
                    "modal": {
                      "type": "popover"
                    }
                  },
                  "fields": [
                    {
                      "validation": [
                        {
                          "rules": [
                            {
                              "flag": "uri",
                              "constraint": {
                                "options": {
                                  "scheme": [
                                    "/^http$/",
                                    "/^https$/",
                                    "/^tel$/",
                                    "/^mailto$/"
                                  ],
                                  "allowRelative": true,
                                  "relativeOnly": false,
                                  "allowCredentials": false
                                }
                              }
                            }
                          ],
                          "level": "error"
                        }
                      ],
                      "description": "A valid web, email, phone, or relative link.",
                      "name": "href",
                      "type": "url",
                      "title": "Link"
                    }
                  ],
                  "name": "link",
                  "type": "object"
                }
              ],
              "decorators": [
                {
                  "value": "strong",
                  "title": "Strong"
                },
                {
                  "value": "em",
                  "title": "Italic"
                },
                {
                  "value": "code",
                  "title": "Code"
                },
                {
                  "value": "underline",
                  "title": "Underline"
                },
                {
                  "value": "strike-through",
                  "title": "Strike"
                }
              ]
            },
            "lists": [
              {
                "value": "bullet",
                "title": "Bulleted list"
              },
              {
                "value": "number",
                "title": "Numbered list"
              }
            ],
            "styles": [
              {
                "value": "normal",
                "title": "Normal"
              },
              {
                "value": "h1",
                "title": "Heading 1"
              },
              {
                "value": "h2",
                "title": "Heading 2"
              },
              {
                "value": "h3",
                "title": "Heading 3"
              },
              {
                "value": "h4",
                "title": "Heading 4"
              },
              {
                "value": "h5",
                "title": "Heading 5"
              },
              {
                "value": "h6",
                "title": "Heading 6"
              },
              {
                "value": "blockquote",
                "title": "Quote"
              }
            ],
            "of": [],
            "type": "block"
          }
        ],
        "name": "content",
        "type": "array"
      }
    ],
    "name": "prose",
    "type": "object"
  },
  {
    "fields": [
      {
        "validation": [
          {
            "rules": [
              {
                "flag": "presence",
                "constraint": "required"
              }
            ],
            "level": "error"
          }
        ],
        "name": "title",
        "type": "string"
      },
      {
        "validation": [
          {
            "rules": [
              {
                "flag": "presence",
                "constraint": "required"
              }
            ],
            "level": "error"
          }
        ],
        "of": [
          {
            "marks": {
              "annotations": [
                {
                  "i18nTitleKey": "inputs.portable-text.annotation.link",
                  "options": {
                    "modal": {
                      "type": "popover"
                    }
                  },
                  "fields": [
                    {
                      "validation": [
                        {
                          "rules": [
                            {
                              "flag": "uri",
                              "constraint": {
                                "options": {
                                  "scheme": [
                                    "/^http$/",
                                    "/^https$/",
                                    "/^tel$/",
                                    "/^mailto$/"
                                  ],
                                  "allowRelative": true,
                                  "relativeOnly": false,
                                  "allowCredentials": false
                                }
                              }
                            }
                          ],
                          "level": "error"
                        }
                      ],
                      "description": "A valid web, email, phone, or relative link.",
                      "name": "href",
                      "type": "url",
                      "title": "Link"
                    }
                  ],
                  "name": "link",
                  "type": "object"
                }
              ],
              "decorators": [
                {
                  "value": "strong",
                  "title": "Strong"
                },
                {
                  "value": "em",
                  "title": "Italic"
                },
                {
                  "value": "code",
                  "title": "Code"
                },
                {
                  "value": "underline",
                  "title": "Underline"
                },
                {
                  "value": "strike-through",
                  "title": "Strike"
                }
              ]
            },
            "lists": [
              {
                "value": "bullet",
                "title": "Bulleted list"
              },
              {
                "value": "number",
                "title": "Numbered list"
              }
            ],
            "styles": [
              {
                "value": "normal",
                "title": "Normal"
              },
              {
                "value": "h1",
                "title": "Heading 1"
              },
              {
                "value": "h2",
                "title": "Heading 2"
              },
              {
                "value": "h3",
                "title": "Heading 3"
              },
              {
                "value": "h4",
                "title": "Heading 4"
              },
              {
                "value": "h5",
                "title": "Heading 5"
              },
              {
                "value": "h6",
                "title": "Heading 6"
              },
              {
                "value": "blockquote",
                "title": "Quote"
              }
            ],
            "of": [],
            "type": "block"
          }
        ],
        "name": "description",
        "type": "array"
      },
      {
        "options": {
          "source": "title"
        },
        "validation": [
          {
            "rules": [
              {
                "flag": "custom"
              },
              {
                "flag": "presence",
                "constraint": "required"
              }
            ],
            "level": "error"
          }
        ],
        "name": "slug",
        "type": "slug"
      },
      {
        "validation": [
          {
            "rules": [
              {
                "flag": "presence",
                "constraint": "required"
              }
            ],
            "level": "error"
          }
        ],
        "name": "seo",
        "type": "seo",
        "title": "SEO"
      },
      {
        "validation": [
          {
            "rules": [
              {
                "flag": "presence",
                "constraint": "required"
              }
            ],
            "level": "error"
          }
        ],
        "fields": [
          {
            "validation": [
              {
                "rules": [
                  {
                    "flag": "presence",
                    "constraint": "required"
                  }
                ],
                "level": "error"
              }
            ],
            "name": "baseId",
            "type": "string",
            "title": "Base ID"
          },
          {
            "validation": [
              {
                "rules": [
                  {
                    "flag": "presence",
                    "constraint": "required"
                  }
                ],
                "level": "error"
              }
            ],
            "name": "tableId",
            "type": "string",
            "title": "Table ID"
          }
        ],
        "name": "airtable",
        "type": "object"
      },
      {
        "validation": [
          {
            "rules": [
              {
                "flag": "presence",
                "constraint": "required"
              }
            ],
            "level": "error"
          }
        ],
        "fields": [
          {
            "initialValue": false,
            "validation": [
              {
                "rules": [
                  {
                    "flag": "presence",
                    "constraint": "required"
                  }
                ],
                "level": "error"
              }
            ],
            "name": "enabled",
            "type": "boolean"
          },
          {
            "name": "priceId",
            "type": "string",
            "title": "Price ID"
          }
        ],
        "name": "stripe",
        "type": "object"
      },
      {
        "validation": [
          {
            "rules": [
              {
                "flag": "presence",
                "constraint": "required"
              }
            ],
            "level": "error"
          }
        ],
        "name": "content",
        "type": "formBuilder"
      }
    ],
    "name": "form",
    "type": "document"
  },
  {
    "of": [
      {
        "type": "input"
      },
      {
        "type": "textarea"
      },
      {
        "type": "select"
      },
      {
        "type": "checkbox"
      }
    ],
    "name": "formBuilder",
    "type": "array"
  },
  {
    "fields": [
      {
        "validation": [
          {
            "rules": [
              {
                "flag": "presence",
                "constraint": "required"
              }
            ],
            "level": "error"
          }
        ],
        "name": "name",
        "type": "string"
      },
      {
        "validation": [
          {
            "rules": [
              {
                "flag": "presence",
                "constraint": "required"
              }
            ],
            "level": "error"
          }
        ],
        "name": "label",
        "type": "string"
      },
      {
        "name": "description",
        "type": "string"
      },
      {
        "name": "placeholder",
        "type": "string"
      },
      {
        "initialValue": true,
        "name": "required",
        "type": "boolean"
      },
      {
        "options": {
          "list": [
            {
              "title": "Text",
              "value": "text"
            },
            {
              "title": "Email",
              "value": "email"
            },
            {
              "title": "Tel",
              "value": "tel"
            },
            {
              "title": "Number",
              "value": "number"
            }
          ]
        },
        "initialValue": "text",
        "name": "type",
        "type": "string"
      },
      {
        "name": "minLength",
        "type": "number"
      },
      {
        "name": "maxLength",
        "type": "number"
      },
      {
        "name": "pattern",
        "type": "string"
      },
      {
        "name": "defaultValue",
        "type": "string"
      }
    ],
    "name": "input",
    "type": "object"
  },
  {
    "fields": [
      {
        "validation": [
          {
            "rules": [
              {
                "flag": "presence",
                "constraint": "required"
              }
            ],
            "level": "error"
          }
        ],
        "name": "name",
        "type": "string"
      },
      {
        "validation": [
          {
            "rules": [
              {
                "flag": "presence",
                "constraint": "required"
              }
            ],
            "level": "error"
          }
        ],
        "name": "label",
        "type": "string"
      },
      {
        "name": "description",
        "type": "string"
      },
      {
        "name": "placeholder",
        "type": "string"
      },
      {
        "initialValue": true,
        "name": "required",
        "type": "boolean"
      },
      {
        "name": "minLength",
        "type": "number"
      },
      {
        "name": "maxLength",
        "type": "number"
      },
      {
        "name": "pattern",
        "type": "string"
      },
      {
        "name": "defaultValue",
        "type": "string"
      }
    ],
    "name": "textarea",
    "type": "object"
  },
  {
    "fields": [
      {
        "validation": [
          {
            "rules": [
              {
                "flag": "presence",
                "constraint": "required"
              }
            ],
            "level": "error"
          }
        ],
        "name": "name",
        "type": "string"
      },
      {
        "validation": [
          {
            "rules": [
              {
                "flag": "presence",
                "constraint": "required"
              }
            ],
            "level": "error"
          }
        ],
        "name": "label",
        "type": "string"
      },
      {
        "name": "description",
        "type": "string"
      },
      {
        "name": "placeholder",
        "type": "string"
      },
      {
        "initialValue": true,
        "name": "required",
        "type": "boolean"
      },
      {
        "validation": [
          {
            "rules": [
              {
                "flag": "presence",
                "constraint": "required"
              }
            ],
            "level": "error"
          }
        ],
        "of": [
          {
            "type": "string"
          }
        ],
        "name": "options",
        "type": "array"
      },
      {
        "name": "defaultValue",
        "type": "string"
      }
    ],
    "name": "select",
    "type": "object"
  },
  {
    "fields": [
      {
        "validation": [
          {
            "rules": [
              {
                "flag": "presence",
                "constraint": "required"
              }
            ],
            "level": "error"
          }
        ],
        "name": "name",
        "type": "string"
      },
      {
        "validation": [
          {
            "rules": [
              {
                "flag": "presence",
                "constraint": "required"
              }
            ],
            "level": "error"
          }
        ],
        "name": "label",
        "type": "string"
      },
      {
        "name": "description",
        "type": "string"
      },
      {
        "initialValue": false,
        "description": "Whether the checkbox must be checked",
        "name": "required",
        "type": "boolean"
      },
      {
        "initialValue": false,
        "description": "Whether the checkbox should be checked by default",
        "name": "defaultValue",
        "type": "boolean"
      }
    ],
    "name": "checkbox",
    "type": "object"
  },
  {
    "fields": [
      {
        "name": "title",
        "type": "string"
      },
      {
        "of": [
          {
            "marks": {
              "annotations": [
                {
                  "i18nTitleKey": "inputs.portable-text.annotation.link",
                  "options": {
                    "modal": {
                      "type": "popover"
                    }
                  },
                  "fields": [
                    {
                      "validation": [
                        {
                          "rules": [
                            {
                              "flag": "uri",
                              "constraint": {
                                "options": {
                                  "scheme": [
                                    "/^http$/",
                                    "/^https$/",
                                    "/^tel$/",
                                    "/^mailto$/"
                                  ],
                                  "allowRelative": true,
                                  "relativeOnly": false,
                                  "allowCredentials": false
                                }
                              }
                            }
                          ],
                          "level": "error"
                        }
                      ],
                      "description": "A valid web, email, phone, or relative link.",
                      "name": "href",
                      "type": "url",
                      "title": "Link"
                    }
                  ],
                  "name": "link",
                  "type": "object"
                }
              ],
              "decorators": [
                {
                  "value": "strong",
                  "title": "Strong"
                },
                {
                  "value": "em",
                  "title": "Italic"
                },
                {
                  "value": "code",
                  "title": "Code"
                },
                {
                  "value": "underline",
                  "title": "Underline"
                },
                {
                  "value": "strike-through",
                  "title": "Strike"
                }
              ]
            },
            "lists": [
              {
                "value": "bullet",
                "title": "Bulleted list"
              },
              {
                "value": "number",
                "title": "Numbered list"
              }
            ],
            "styles": [
              {
                "value": "normal",
                "title": "Normal"
              },
              {
                "value": "h1",
                "title": "Heading 1"
              },
              {
                "value": "h2",
                "title": "Heading 2"
              },
              {
                "value": "h3",
                "title": "Heading 3"
              },
              {
                "value": "h4",
                "title": "Heading 4"
              },
              {
                "value": "h5",
                "title": "Heading 5"
              },
              {
                "value": "h6",
                "title": "Heading 6"
              },
              {
                "value": "blockquote",
                "title": "Quote"
              }
            ],
            "of": [],
            "type": "block"
          }
        ],
        "name": "description",
        "type": "array"
      }
    ],
    "name": "events",
    "type": "object"
  },
  {
    "fields": [
      {
        "validation": [
          {
            "rules": [
              {
                "flag": "presence",
                "constraint": "required"
              }
            ],
            "level": "error"
          }
        ],
        "name": "title",
        "type": "string"
      },
      {
        "validation": [
          {
            "rules": [
              {
                "flag": "presence",
                "constraint": "required"
              }
            ],
            "level": "error"
          }
        ],
        "name": "description",
        "type": "text"
      },
      {
        "options": {
          "hotspot": true
        },
        "fields": [
          {
            "name": "alt",
            "type": "string",
            "title": "Alt Text"
          }
        ],
        "name": "image",
        "type": "image"
      },
      {
        "initialValue": false,
        "validation": [
          {
            "rules": [
              {
                "flag": "presence",
                "constraint": "required"
              }
            ],
            "level": "error"
          }
        ],
        "name": "noIndex",
        "type": "boolean",
        "title": "Hide from search engines?"
      }
    ],
    "name": "seo",
    "type": "object",
    "title": "SEO"
  }
]
